promptpal/__init__.py
promptpal/promptpal.py
promptpal/promptpal_ui.py
promptpal/roles/__init__.py
promptpal/roles/role.py
promptpal/roles/role_schema.py
promptpal/roles/role_schema.yaml
promptpal/roles/roles.yaml
promptpal-2.0.5.dist-info/LICENSE.txt
promptpal-2.0.5.dist-info/METADATA
promptpal-2.0.5.dist-info/WHEEL
promptpal-2.0.5.dist-info/top_level.txt
promptpal-2.0.5.dist-info/RECORD
