Metadata-Version: 2.2
Name: promptpal
Version: 2.0.5
Summary: Python based tool for improved LLM interactions using the Gemini API.
Author-email: Matt Jenior <mattjenior@gmail.com>
License: MIT
Project-URL: Homepage, https://github.com/mattjenior/promptpal
Project-URL: Documentation, https://github.com/mattjenior/promptpal#readme
Project-URL: Repository, https://github.com/mattjenior/promptpal.git
Project-URL: Issues, https://github.com/mattjenior/promptpal/issues
Project-URL: Changelog, https://github.com/mattjenior/promptpal/blob/main/CHANGELOG.md
Keywords: llm,ai,gemini,prompt-engineering
Classifier: Development Status :: 4 - Beta
Classifier: Intended Audience :: Developers
Classifier: License :: OSI Approved :: MIT License
Classifier: Operating System :: OS Independent
Classifier: Programming Language :: Python :: 3
Classifier: Programming Language :: Python :: 3.11
Classifier: Topic :: Software Development :: Libraries :: Python Modules
Classifier: Topic :: Scientific/Engineering :: Artificial Intelligence
Requires-Python: >=3.11
License-File: LICENSE.txt
Requires-Dist: google-genai>=1.2.0
Requires-Dist: ipywidgets>=8.0.0
Requires-Dist: pillow>=10.2.0
Requires-Dist: pyyaml>=6.0.1
Requires-Dist: pytest-mock>=3.14.0
Requires-Dist: jsonschema>=4.21.1
Provides-Extra: dev
Requires-Dist: pytest>=8.3.4; extra == "dev"
Requires-Dist: pytest-cov>=4.1.0; extra == "dev"
Requires-Dist: ruff>=0.9.5; extra == "dev"
Requires-Dist: build>=1.0.3; extra == "dev"
Requires-Dist: twine>=4.0.2; extra == "dev"
